[
    {
        "team1": {
            "players": ["NADAL Rafael"],
            "score": 4
        },
        "team2": {
            "players": ["FEDERER Roger"],
            "score": 4
        },
        "date": "2017-01-01",
        "startTime": "15:00",
        "duration": "2:00",
        "court": "le super court1"
    },
    {
        "team1": {
            "players": ["MURRAY Andy"],
            "score": 4
        },
        "team2": {
            "players": ["ZVEREV Alexander"],
            "score": 0
        },
        "date": "2017-01-01",
        "startTime": "17:00",
        "duration": "1:00",
        "court": "le super court2"
    },
    {
        "team1": {
            "players": ["CILIC Marin", "NADAL Rafael"],
            "score": 6
        },
        "team2": {
            "players": ["DJOKOVIC Novak", "FEDERER Roger"],
            "score": 5
        },
        "date": "2017-01-01",
        "startTime": "12:00",
        "duration": "1:00",
        "court": "le super court3"
    },
    {
        "team1": {
            "players": ["THIEM Dominic", "NADAL Rafael"],
            "score": 5
        },
        "team2": {
            "players": ["DIMITROV Grigor", "FEDERER Roger"],
            "score": 1
        },
        "date": "2017-01-01",
        "startTime": "12:00",
        "duration": "4:00",
        "court": "le super court4"
    },
    {
        "team1": {
            "players": ["WAWRINKA Stan"],
            "score": 6
        },
        "team2": {
            "players": ["CARRENO BUSTA Pablo"],
            "score": 4
        },
        "date": "2017-01-01",
        "startTime": "18:00",
        "duration": "3:00",
        "court": "le super court5"
    }
]